sqlalchemy_tenants/__init__.py
sqlalchemy_tenants/core.py
sqlalchemy_tenants/exceptions.py
sqlalchemy_tenants/managers.py
sqlalchemy_tenants/py.typed
sqlalchemy_tenants/utils.py
sqlalchemy_tenants/aio/__init__.py
sqlalchemy_tenants/aio/managers.py
sqlalchemy_tenants-0.2.0.dist-info/METADATA
sqlalchemy_tenants-0.2.0.dist-info/WHEEL
sqlalchemy_tenants-0.2.0.dist-info/licenses/LICENSE
sqlalchemy_tenants-0.2.0.dist-info/RECORD
