Metadata-Version: 2.4
Name: sqlalchemy-tenants
Version: 0.2.0
Summary: Add your description here
Author-email: Michele Zanotti <m.zanotti019@gmail.com>
License-File: LICENSE
Requires-Python: <=3.14,>=3.10
Requires-Dist: alembic>=1.10.0
Requires-Dist: sqlalchemy>=2.0.0
